thispackagedoesnotexist/__init__.py
thispackagedoesnotexist/connection.py
thispackagedoesnotexist/features/__init__.py
thispackagedoesnotexist/features/browser.py
thispackagedoesnotexist/features/client.py
thispackagedoesnotexist/features/filemanager.py
thispackagedoesnotexist/features/microphone.py
thispackagedoesnotexist/features/power.py
thispackagedoesnotexist/features/proxy.py
thispackagedoesnotexist/features/remotedesktop.py
thispackagedoesnotexist/features/screenshot.py
thispackagedoesnotexist/features/terminal.py
thispackagedoesnotexist/features/webcam.py
thispackagedoesnotexist/plugins/__init__.py
thispackagedoesnotexist/plugins/chunks.py
thispackagedoesnotexist/plugins/client.py
thispackagedoesnotexist/plugins/converter.py
thispackagedoesnotexist/plugins/firewall.py
thispackagedoesnotexist/plugins/fm.py
thispackagedoesnotexist/plugins/info.py
thispackagedoesnotexist/plugins/shared.py
thispackagedoesnotexist/plugins/shell.py
thispackagedoesnotexist/plugins/proxy/reverse.exe
thispackagedoesnotexist-0.8.6.dist-info/METADATA
thispackagedoesnotexist-0.8.6.dist-info/WHEEL
thispackagedoesnotexist-0.8.6.dist-info/top_level.txt
thispackagedoesnotexist-0.8.6.dist-info/RECORD
